slackbot/__init__.py
slackbot/bot.py
slackbot/dispatcher.py
slackbot/manager.py
slackbot/settings.py
slackbot/slackclient.py
slackbot/utils.py
slackbot/plugins/__init__.py
slackbot/plugins/hello.py
slackbot/plugins/upload.py
slackbotng-1.1.3.dist-info/LICENSE.txt
slackbotng-1.1.3.dist-info/METADATA
slackbotng-1.1.3.dist-info/WHEEL
slackbotng-1.1.3.dist-info/top_level.txt
slackbotng-1.1.3.dist-info/RECORD
