Metadata-Version: 2.1
Name: slackbotng
Version: 1.1.3
Summary: A simple chat bot for Slack
Home-page: http://github.com/amuraru/slackbot
Author: Adrian Muraru
Author-email: adi.muraru@gmail.com
License: MIT
Platform: Any
Classifier: Development Status :: 4 - Beta
Classifier: License :: OSI Approved :: MIT License
Classifier: Operating System :: OS Independent
Classifier: Programming Language :: Python
Classifier: Programming Language :: Python :: 2
Classifier: Programming Language :: Python :: 2.7
Classifier: Programming Language :: Python :: 3
Classifier: Programming Language :: Python :: 3.6
License-File: LICENSE.txt
Requires-Dist: requests
Requires-Dist: websocket-client
Requires-Dist: slack-sdk
